dryorm/__init__.py
dryorm/models.py
dryorm/mixin.py
dryorm/psql/__init__.py
dryorm/psql/mixin.py
dryorm/psql/models.py
dryorm/sqlite/mixin.py
dryorm/sqlite/models.py
dryorm/sqlite/__init__.py
DRY_orm-0.0.61.dist-info/top_level.txt
DRY_orm-0.0.61.dist-info/METADATA
DRY_orm-0.0.61.dist-info/DESCRIPTION.rst
DRY_orm-0.0.61.dist-info/metadata.json
DRY_orm-0.0.61.dist-info/WHEEL
DRY_orm-0.0.61.dist-info/RECORD
