Metadata-Version: 2.0
Name: DRY-orm
Version: 0.0.61
Summary: DRY is inspired by Django-ORM
Home-page: UNKNOWN
Author: Jorge Alpedrinha Ramos
Author-email: jalpedrinharamos@gmail.com
License: LICENSE.txt
Platform: UNKNOWN
Requires-Dist: psycopg2
